pip_manager/__init__.py
pip_manager/app.py
pip_manager/config.ini
pip_manager/distribution.py
pip_manager/gui.py
pip_manager/run.py
pip_manager/utils.py
pip_manager-1.0.4.dist-info/LICENSE.txt
pip_manager-1.0.4.dist-info/METADATA
pip_manager-1.0.4.dist-info/WHEEL
pip_manager-1.0.4.dist-info/entry_points.txt
pip_manager-1.0.4.dist-info/top_level.txt
pip_manager-1.0.4.dist-info/RECORD
