Metadata-Version: 2.1
Name: pip-manager
Version: 1.0.4
Summary: pip-manager is a command line tool to make Python packages management easy.
Home-page: https://github.com/kchomski/pip-manager
Author: Krzysztof Chomski
Author-email: krzysztof.chomski@gmail.com
License: MIT
Platform: UNKNOWN
Classifier: Development Status :: 5 - Production/Stable
Classifier: Environment :: Console
Classifier: Intended Audience :: Developers
Classifier: License :: OSI Approved :: MIT License
Classifier: Operating System :: POSIX :: Linux
Classifier: Operating System :: Microsoft :: Windows
Classifier: Programming Language :: Python :: 2.7
Classifier: Programming Language :: Python :: 3.5
Classifier: Programming Language :: Python :: 3.6
Classifier: Programming Language :: Python :: 3.7
Classifier: Topic :: Software Development
Classifier: Topic :: Utilities
Requires-Dist: pip
